{
  "type": "doc",
  "content": [
    {
      "type": "heading",
      "attrs": {
        "name": "heading",
        "id": "8Rua137n7uCyV4Kkcfpus",
        "level": 1
      },
      "content": [
        {
          "type": "text",
          "text": "Rich Text Editor with Tiptap and Vue.js"
        }
      ]
    },
    {
      "type": "heading",
      "attrs": {
        "name": "heading",
        "id": "VST6oRWDuGvvIzcA6yVvu",
        "level": 2
      },
      "content": [
        {
          "type": "text",
          "text": "Introduction "
        }
      ]
    },
    {
      "type": "paragraph",
      "attrs": {
        "name": "paragraph",
        "id": "-uCHLdEPLCzxVU3mDe5DK"
      },
      "content": [
        {
          "type": "text",
          "text": "As a playground for rich text editors with Tiptap, committed to exploring and incubating various practical extensions.  "
        }
      ]
    },
    {
      "type": "heading",
      "attrs": {
        "name": "heading",
        "id": "DnUMiiSteEndjxmOtfqcB",
        "level": 2
      },
      "content": [
        {
          "type": "text",
          "text": "Features"
        }
      ]
    },
    {
      "type": "heading",
      "attrs": {
        "name": "heading",
        "id": "eI4PgstgwwIC-dIX76DUO",
        "level": 3
      },
      "content": [
        {
          "type": "text",
          "text": "Slash Menu"
        }
      ]
    },
    {
      "type": "paragraph",
      "attrs": {
        "name": "heading",
        "id": "hbfVe7-29ZOVcObO6l2NQ"
      },
      "content": [
        {
          "type": "text",
          "text": "Trigger menu by typing \"/\""
        }
      ]
    },
    {
      "type": "heading",
      "attrs": {
        "name": "heading",
        "id": "jmnRV00abOr0Mqnu0AMH1",
        "level": 3
      },
      "content": [
        {
          "type": "text",
          "text": "Handle"
        }
      ]
    },
    {
      "type": "paragraph",
      "attrs": {
        "name": "heading",
        "id": "6mhi5AAbqtC03mzGEUi8q"
      },
      "content": [
        {
          "type": "text",
          "text": "Added handle on the left :"
        }
      ]
    },
    {
      "type": "bulletList",
      "attrs": {
        "name": "bulletList",
        "id": "oXSbKklav4hLWres_hO53"
      },
      "content": [
        {
          "type": "listItem",
          "content": [
            {
              "type": "paragraph",
              "attrs": {
                "name": "heading",
                "id": "8jBjSuCGHPXMhaptm_sjf"
              },
              "content": [
                {
                  "type": "text",
                  "text": "Click the add icon to trigger slash menu"
                }
              ]
            }
          ]
        },
        {
          "type": "listItem",
          "content": [
            {
              "type": "paragraph",
              "attrs": {
                "name": "heading",
                "id": "wDo_jP4YYYsJaExvjY3Fc"
              },
              "content": [
                {
                  "type": "text",
                  "text": "Drag the node"
                }
              ]
            }
          ]
        }
      ]
    },
    {
      "type": "heading",
      "attrs": {
        "name": "heading",
        "id": "-JrLKI094ml7tvxNDlJOT",
        "level": 3
      },
      "content": [
        {
          "type": "text",
          "text": "Symbol"
        }
      ]
    },
    {
      "type": "paragraph",
      "attrs": {
        "name": "heading",
        "id": "TTkanFDYRQMAzrXCJiHtO"
      },
      "content": [
        {
          "type": "text",
          "text": "Add metadata for node :"
        }
      ]
    },
    {
      "type": "bulletList",
      "attrs": {
        "name": "bulletList",
        "id": "shMiZH0hlroVjgG2JEpHO"
      },
      "content": [
        {
          "type": "listItem",
          "content": [
            {
              "type": "paragraph",
              "attrs": {
                "name": "heading",
                "id": "uO7UUHhE4msH2MSao8-tO"
              },
              "content": [
                {
                  "type": "text",
                  "text": "data-name"
                }
              ]
            }
          ]
        },
        {
          "type": "listItem",
          "content": [
            {
              "type": "paragraph",
              "attrs": {
                "name": "heading",
                "id": "9kXs49Gr5cN6JmEOZAuQM"
              },
              "content": [
                {
                  "type": "text",
                  "text": "data-id"
                }
              ]
            }
          ]
        }
      ]
    }
  ]
}
